{"markdown":"[Unsplash logoUnsplash Home](https://unsplash.com/)\n\n# Pagenotfound\n\nHmm, the page you were looking for doesn’t seem to exist anymore.\n\n[Back to Unsplash](https://unsplash.com/)\n\nPhoto by [@nasa](https://unsplash.com/@nasa)\n\n404","metadata":{"viewport":"width=device-width, initial-scale=1","robots":"noindex, nofollow","language":"en-US","title":"Page not found | Unsplash","scrapeId":"019df272-4ec3-7419-a5b7-9d4bff823a62","sourceURL":"https://unsplash.com/photos/NPhvT4JIBvg","url":"https://unsplash.com/photos/NPhvT4JIBvg","statusCode":404,"error":"Not Found","contentType":"text/html; charset=utf-8","timezone":"America/New_York","proxyUsed":"basic","cacheState":"miss","indexId":"73efc3c7-b1ae-4967-9be2-68741ab60750","creditsUsed":1,"concurrencyLimited":false}}